pygharar/__init__.py
pygharar/adaptors.py
pygharar/backoff.py
pygharar/gharar.py
pygharar/http_base.py
pygharar/requrements.txt
pygharar-0.0.2.dist-info/LICENSE
pygharar-0.0.2.dist-info/WHEEL
pygharar-0.0.2.dist-info/METADATA
pygharar-0.0.2.dist-info/RECORD
